termapod/__init__.py
termapod/_version.py
termapod/termapod.py
termapod-0.1.3.dist-info/LICENSE
termapod-0.1.3.dist-info/METADATA
termapod-0.1.3.dist-info/WHEEL
termapod-0.1.3.dist-info/entry_points.txt
termapod-0.1.3.dist-info/top_level.txt
termapod-0.1.3.dist-info/RECORD
