Metadata-Version: 2.1
Name: termapod
Version: 0.1.3
Summary: An ASCII block / ANSI color renderer for NASA's Astonomy Pic of the Day. For like no reason.
Author-email: Trevor Schrock <spacemeat@gmail.com>
Maintainer-email: Trevor Schrock <spacemeat@gmail.com>
License: MIT License
Project-URL: Repository, https://github.com/spacemeat/termapod
Keywords: astronomy,NASA,ASCII,ANSI
Classifier: Development Status :: 4 - Beta
Classifier: Intended Audience :: End Users/Desktop
Classifier: Programming Language :: Python :: 3.10
Classifier: Environment :: Console
Classifier: License :: OSI Approved :: MIT License
Classifier: Topic :: Scientific/Engineering :: Astronomy
Requires-Python: >=3.10
License-File: LICENSE
Requires-Dist: pillow ==10.3.0
Requires-Dist: requests ==2.31.0
